audiocaps_download/Downloader.py
audiocaps_download/__init__.py
audiocaps_download-1.1.dist-info/METADATA
audiocaps_download-1.1.dist-info/WHEEL
audiocaps_download-1.1.dist-info/top_level.txt
audiocaps_download-1.1.dist-info/RECORD
