Metadata-Version: 2.1
Name: audiocaps-download
Version: 1.1
Summary: This package aims at simplifying the download of the AudioCaps dataset.
Home-page: https://github.com/MorenoLaQuatra/audiocaps-download
Author: Moreno La Quatra
Author-email: moreno.laquatra@gmail.com
Classifier: Programming Language :: Python :: 3.9
Classifier: License :: OSI Approved :: GNU General Public License v3 (GPLv3)
Classifier: Programming Language :: Python :: 3.7
Classifier: Programming Language :: Python :: 3.8
Classifier: Programming Language :: Python :: 3
Classifier: Operating System :: OS Independent
Requires-Dist: joblib
Requires-Dist: pandas
Requires-Dist: yt-dlp
Provides-Extra: dev
Requires-Dist: pytest >=3.7 ; extra == 'dev'
